usb_scanner/__init__.py
usb_scanner/exceptions.py
usb_scanner/mapping.py
usb_scanner/usb_devices.py
usb_scanner-0.0.8.dist-info/licenses/LICENSE
usb_scanner-0.0.8.dist-info/METADATA
usb_scanner-0.0.8.dist-info/WHEEL
usb_scanner-0.0.8.dist-info/top_level.txt
usb_scanner-0.0.8.dist-info/RECORD
