Metadata-Version: 2.4
Name: usb_scanner
Version: 0.0.8
Summary: For use USB barcode scanners
Home-page: https://github.com/Nels885/usb_scanner
Author: Lionel VOIRIN
Author-email: nels885@protonmail.com
Classifier: Programming Language :: Python :: 3
Classifier: License :: OSI Approved :: MIT License
Classifier: Operating System :: POSIX :: Linux
Requires-Python: >=3.7
License-File: LICENSE
Dynamic: license-file
